MANIFEST.in
setup.cfg
setup.py
question_creation_distributable_app/User.sqlite3
question_creation_distributable_app/User.txt
question_creation_distributable_app/__main__.py
question_creation_distributable_app/auth.py
question_creation_distributable_app/data_process.py
question_creation_distributable_app/load_data.py
question_creation_distributable_app/requirements.txt
question_creation_distributable_app.egg-info/PKG-INFO
question_creation_distributable_app.egg-info/SOURCES.txt
question_creation_distributable_app.egg-info/dependency_links.txt
question_creation_distributable_app.egg-info/entry_points.txt
question_creation_distributable_app.egg-info/requires.txt
question_creation_distributable_app.egg-info/top_level.txt
question_creation_distributable_app/cloud_backup/User.sqlite3
question_creation_distributable_app/react/build/asset-manifest.json
question_creation_distributable_app/react/build/favicon.ico
question_creation_distributable_app/react/build/index.html
question_creation_distributable_app/react/build/logo192.png
question_creation_distributable_app/react/build/logo512.png
question_creation_distributable_app/react/build/manifest.json
question_creation_distributable_app/react/build/robots.txt
question_creation_distributable_app/react/build/static/css/2.9a2a5986.chunk.css
question_creation_distributable_app/react/build/static/css/2.9a2a5986.chunk.css.map
question_creation_distributable_app/react/build/static/css/main.605b9150.chunk.css
question_creation_distributable_app/react/build/static/css/main.605b9150.chunk.css.map
question_creation_distributable_app/react/build/static/js/2.8705c7e6.chunk.js
question_creation_distributable_app/react/build/static/js/2.8705c7e6.chunk.js.LICENSE.txt
question_creation_distributable_app/react/build/static/js/2.8705c7e6.chunk.js.map
question_creation_distributable_app/react/build/static/js/3.94c7fce7.chunk.js
question_creation_distributable_app/react/build/static/js/3.94c7fce7.chunk.js.map
question_creation_distributable_app/react/build/static/js/main.4cadf675.chunk.js
question_creation_distributable_app/react/build/static/js/main.4cadf675.chunk.js.map
question_creation_distributable_app/react/build/static/js/runtime-main.a048ddd9.js
question_creation_distributable_app/react/build/static/js/runtime-main.a048ddd9.js.map
